[{"locations": 229, "pct": 0, "amount": 1070060, "meters": 0, "meters_rdof": 1, "geoid": "390197201002"}, {"locations": 96, "pct": 1, "amount": 454640, "meters": 0, "meters_rdof": 1, "geoid": "390197202003"}, {"locations": 135, "pct": 1, "amount": 395370, "meters": 0, "meters_rdof": 1, "geoid": "390197203001"}, {"locations": 57, "pct": 2, "amount": 257890, "meters": 0, "meters_rdof": 1, "geoid": "390197203003"}, {"locations": 2, "pct": 50, "amount": 26900, "meters": 0, "meters_rdof": 1, "geoid": "390197203005"}, {"locations": 716, "pct": 0, "amount": 3195910, "meters": 0, "meters_rdof": 1, "geoid": "390197204001"}, {"locations": 133, "pct": 1, "amount": 426540, "meters": 0, "meters_rdof": 1, "geoid": "390197204002"}, {"locations": 49, "pct": 2, "amount": 58880, "meters": 0, "meters_rdof": 1, "geoid": "390197204003"}, {"locations": 11, "pct": 9, "amount": 83360, "meters": 0, "meters_rdof": 1, "geoid": "390197204004"}, {"locations": 116, "pct": 1, "amount": 454900, "meters": 0, "meters_rdof": 1, "geoid": "390197205002"}, {"locations": 63, "pct": 2, "amount": 124420, "meters": 0, "meters_rdof": 1, "geoid": "390197205005"}, {"locations": 355, "pct": 0, "amount": 2276750, "meters": 0, "meters_rdof": 1, "geoid": "390197206001"}, {"locations": 455, "pct": 0, "amount": 3583780, "meters": 0, "meters_rdof": 1, "geoid": "390197206003"}, {"locations": 17, "pct": 6, "amount": 51560, "meters": 0, "meters_rdof": 1, "geoid": "390299512004"}, {"locations": 396, "pct": 0, "amount": 1462030, "meters": 0, "meters_rdof": 1, "geoid": "390299513003"}, {"locations": 359, "pct": 0, "amount": 2572950, "meters": 0, "meters_rdof": 1, "geoid": "390679756001"}, {"locations": 244, "pct": 0, "amount": 1419190, "meters": 0, "meters_rdof": 1, "geoid": "390679756002"}, {"locations": 188, "pct": 1, "amount": 1713000, "meters": 0, "meters_rdof": 1, "geoid": "390810110002"}, {"locations": 52, "pct": 2, "amount": 526960, "meters": 0, "meters_rdof": 1, "geoid": "390810111002"}, {"locations": 345, "pct": 0, "amount": 2511590, "meters": 0, "meters_rdof": 1, "geoid": "390810111003"}, {"locations": 92, "pct": 1, "amount": 266730, "meters": 0, "meters_rdof": 1, "geoid": "390810114023"}, {"locations": 124, "pct": 1, "amount": 562930, "meters": 0, "meters_rdof": 1, "geoid": "391570204003"}, {"locations": 162, "pct": 1, "amount": 675870, "meters": 0, "meters_rdof": 1, "geoid": "391570204004"}]