[{"locations": 230, "pct": 0, "amount": 1035140, "meters": 1, "meters_rdof": 1, "geoid": "280059501001"}, {"locations": 285, "pct": 0, "amount": 902110, "meters": 1, "meters_rdof": 1, "geoid": "280059501002"}, {"locations": 470, "pct": 0, "amount": 2074120, "meters": 1, "meters_rdof": 1, "geoid": "280059501003"}, {"locations": 49, "pct": 2, "amount": 102040, "meters": 1, "meters_rdof": 1, "geoid": "280059501004"}, {"locations": 332, "pct": 0, "amount": 1678980, "meters": 1, "meters_rdof": 1, "geoid": "280059501005"}, {"locations": 431, "pct": 0, "amount": 2365550, "meters": 1, "meters_rdof": 1, "geoid": "280059502001"}, {"locations": 458, "pct": 0, "amount": 2242570, "meters": 1, "meters_rdof": 1, "geoid": "280059502003"}, {"locations": 390, "pct": 0, "amount": 1875070, "meters": 1, "meters_rdof": 1, "geoid": "280059503001"}, {"locations": 424, "pct": 0, "amount": 2472210, "meters": 1, "meters_rdof": 1, "geoid": "280059503002"}, {"locations": 550, "pct": 0, "amount": 2936980, "meters": 1, "meters_rdof": 1, "geoid": "280059503003"}, {"locations": 391, "pct": 0, "amount": 1467220, "meters": 1, "meters_rdof": 1, "geoid": "280059503004"}, {"locations": 577, "pct": 0, "amount": 2969030, "meters": 1, "meters_rdof": 1, "geoid": "280059503005"}, {"locations": 314, "pct": 0, "amount": 925320, "meters": 1, "meters_rdof": 1, "geoid": "280239502001"}, {"locations": 191, "pct": 1, "amount": 889620, "meters": 1, "meters_rdof": 1, "geoid": "280239502003"}, {"locations": 342, "pct": 0, "amount": 1347420, "meters": 1, "meters_rdof": 1, "geoid": "280239503001"}, {"locations": 279, "pct": 0, "amount": 1589970, "meters": 1, "meters_rdof": 1, "geoid": "280239503004"}, {"locations": 19, "pct": 5, "amount": 66370, "meters": 1, "meters_rdof": 1, "geoid": "280299501001"}, {"locations": 160, "pct": 1, "amount": 397110, "meters": 1, "meters_rdof": 1, "geoid": "280299502001"}, {"locations": 130, "pct": 1, "amount": 192600, "meters": 1, "meters_rdof": 1, "geoid": "280299502002"}, {"locations": 72, "pct": 1, "amount": 101380, "meters": 1, "meters_rdof": 1, "geoid": "280299502003"}, {"locations": 443, "pct": 0, "amount": 1496140, "meters": 1, "meters_rdof": 1, "geoid": "280299502004"}, {"locations": 21, "pct": 5, "amount": 240770, "meters": 1, "meters_rdof": 1, "geoid": "280299502005"}, {"locations": 20, "pct": 5, "amount": 33230, "meters": 1, "meters_rdof": 1, "geoid": "280299504001"}, {"locations": 59, "pct": 2, "amount": 97520, "meters": 1, "meters_rdof": 1, "geoid": "280299504002"}, {"locations": 26, "pct": 4, "amount": 26850, "meters": 1, "meters_rdof": 1, "geoid": "280299504003"}, {"locations": 77, "pct": 1, "amount": 58950, "meters": 1, "meters_rdof": 1, "geoid": "280299504004"}, {"locations": 62, "pct": 2, "amount": 28400, "meters": 1, "meters_rdof": 1, "geoid": "280299504005"}, {"locations": 510, "pct": 0, "amount": 3473240, "meters": 1, "meters_rdof": 1, "geoid": "280299505001"}, {"locations": 668, "pct": 0, "amount": 1743180, "meters": 1, "meters_rdof": 1, "geoid": "280299505002"}, {"locations": 431, "pct": 0, "amount": 1245790, "meters": 2, "meters_rdof": 2, "geoid": "280299505003"}, {"locations": 78, "pct": 3, "amount": 141320, "meters": 2, "meters_rdof": 2, "geoid": "280299505004"}, {"locations": 207, "pct": 0, "amount": 783980, "meters": 1, "meters_rdof": 1, "geoid": "280299506001"}, {"locations": 304, "pct": 0, "amount": 1735420, "meters": 1, "meters_rdof": 1, "geoid": "280299506002"}, {"locations": 612, "pct": 0, "amount": 1051410, "meters": 1, "meters_rdof": 1, "geoid": "280319501001"}, {"locations": 578, "pct": 0, "amount": 1185240, "meters": 1, "meters_rdof": 1, "geoid": "280319501002"}, {"locations": 571, "pct": 0, "amount": 1506920, "meters": 1, "meters_rdof": 1, "geoid": "280319501003"}, {"locations": 5, "pct": 20, "amount": 45970, "meters": 1, "meters_rdof": 1, "geoid": "280319502001"}, {"locations": 259, "pct": 0, "amount": 598550, "meters": 1, "meters_rdof": 1, "geoid": "280319503001"}, {"locations": 25, "pct": 4, "amount": 50630, "meters": 1, "meters_rdof": 1, "geoid": "280319503002"}, {"locations": 436, "pct": 0, "amount": 1270140, "meters": 1, "meters_rdof": 1, "geoid": "280319503003"}, {"locations": 211, "pct": 0, "amount": 590430, "meters": 1, "meters_rdof": 1, "geoid": "280319503004"}, {"locations": 482, "pct": 0, "amount": 1132810, "meters": 1, "meters_rdof": 1, "geoid": "280319504001"}, {"locations": 606, "pct": 0, "amount": 1356030, "meters": 1, "meters_rdof": 1, "geoid": "280319504002"}, {"locations": 640, "pct": 0, "amount": 1434290, "meters": 1, "meters_rdof": 1, "geoid": "280319504003"}, {"locations": 521, "pct": 0, "amount": 1151340, "meters": 1, "meters_rdof": 1, "geoid": "280319504004"}, {"locations": 5, "pct": 20, "amount": 2450, "meters": 1, "meters_rdof": 1, "geoid": "280350010001"}, {"locations": 2, "pct": 50, "amount": 2190, "meters": 1, "meters_rdof": 1, "geoid": "280350010002"}, {"locations": 12, "pct": 8, "amount": 19010, "meters": 2, "meters_rdof": 1, "geoid": "280350102001"}, {"locations": 101, "pct": 1, "amount": 114920, "meters": 1, "meters_rdof": 1, "geoid": "280350102002"}, {"locations": 82, "pct": 1, "amount": 54900, "meters": 1, "meters_rdof": 1, "geoid": "280350102003"}, {"locations": 19, "pct": 5, "amount": 54510, "meters": 1, "meters_rdof": 1, "geoid": "280350102004"}, {"locations": 47, "pct": 2, "amount": 433730, "meters": 1, "meters_rdof": 1, "geoid": "280379501002"}, {"locations": 196, "pct": 1, "amount": 1134650, "meters": 1, "meters_rdof": 1, "geoid": "280379501003"}, {"locations": 139, "pct": 1, "amount": 302590, "meters": 1, "meters_rdof": 1, "geoid": "280490112024"}, {"locations": 48, "pct": 2, "amount": 126460, "meters": 1, "meters_rdof": 1, "geoid": "280619503004"}, {"locations": 129, "pct": 1, "amount": 303630, "meters": 1, "meters_rdof": 1, "geoid": "280619504001"}, {"locations": 135, "pct": 1, "amount": 326440, "meters": 1, "meters_rdof": 1, "geoid": "280619504002"}, {"locations": 9, "pct": 11, "amount": 18980, "meters": 1, "meters_rdof": 1, "geoid": "280619504003"}, {"locations": 245, "pct": 0, "amount": 629010, "meters": 1, "meters_rdof": 1, "geoid": "280619504004"}, {"locations": 63, "pct": 2, "amount": 340430, "meters": 1, "meters_rdof": 1, "geoid": "280659501001"}, {"locations": 71, "pct": 1, "amount": 445470, "meters": 1, "meters_rdof": 1, "geoid": "280659501002"}, {"locations": 129, "pct": 1, "amount": 415690, "meters": 1, "meters_rdof": 1, "geoid": "280659501003"}, {"locations": 98, "pct": 1, "amount": 334880, "meters": 1, "meters_rdof": 1, "geoid": "280659501004"}, {"locations": 8, "pct": 12, "amount": 15070, "meters": 1, "meters_rdof": 1, "geoid": "280659501005"}, {"locations": 124, "pct": 1, "amount": 722310, "meters": 1, "meters_rdof": 1, "geoid": "280659502011"}, {"locations": 183, "pct": 1, "amount": 835430, "meters": 1, "meters_rdof": 1, "geoid": "280659502012"}, {"locations": 100, "pct": 1, "amount": 357200, "meters": 1, "meters_rdof": 1, "geoid": "280659502013"}, {"locations": 300, "pct": 0, "amount": 2089960, "meters": 1, "meters_rdof": 1, "geoid": "280659502021"}, {"locations": 340, "pct": 0, "amount": 1499360, "meters": 1, "meters_rdof": 1, "geoid": "280659502022"}, {"locations": 199, "pct": 1, "amount": 793980, "meters": 1, "meters_rdof": 1, "geoid": "280659502023"}, {"locations": 29, "pct": 3, "amount": 37030, "meters": 1, "meters_rdof": 1, "geoid": "280659502024"}, {"locations": 21, "pct": 5, "amount": 95740, "meters": 1, "meters_rdof": 1, "geoid": "280679501002"}, {"locations": 27, "pct": 4, "amount": 1240, "meters": 1, "meters_rdof": 1, "geoid": "280679501005"}, {"locations": 563, "pct": 0, "amount": 1164170, "meters": 1, "meters_rdof": 1, "geoid": "280679511001"}, {"locations": 162, "pct": 1, "amount": 422120, "meters": 1, "meters_rdof": 1, "geoid": "280679511003"}, {"locations": 203, "pct": 0, "amount": 357190, "meters": 1, "meters_rdof": 1, "geoid": "280730201001"}, {"locations": 2, "pct": 50, "amount": 2560, "meters": 1, "meters_rdof": 1, "geoid": "280730202023"}, {"locations": 1, "pct": 100, "amount": 4020, "meters": 1, "meters_rdof": 1, "geoid": "280730203021"}, {"locations": 25, "pct": 4, "amount": 195530, "meters": 1, "meters_rdof": 1, "geoid": "280779601001"}, {"locations": 209, "pct": 0, "amount": 370280, "meters": 1, "meters_rdof": 1, "geoid": "280779601002"}, {"locations": 352, "pct": 0, "amount": 1580710, "meters": 1, "meters_rdof": 1, "geoid": "280779601003"}, {"locations": 424, "pct": 0, "amount": 1555170, "meters": 1, "meters_rdof": 1, "geoid": "280779601004"}, {"locations": 589, "pct": 0, "amount": 1876230, "meters": 2, "meters_rdof": 2, "geoid": "280779602001"}, {"locations": 280, "pct": 1, "amount": 921660, "meters": 2, "meters_rdof": 2, "geoid": "280779602002"}, {"locations": 41, "pct": 2, "amount": 33070, "meters": 1, "meters_rdof": 1, "geoid": "280779602003"}, {"locations": 8, "pct": 12, "amount": 6240, "meters": 1, "meters_rdof": 1, "geoid": "280779602004"}, {"locations": 434, "pct": 0, "amount": 994190, "meters": 2, "meters_rdof": 2, "geoid": "280779603001"}, {"locations": 449, "pct": 0, "amount": 927940, "meters": 2, "meters_rdof": 2, "geoid": "280779603002"}, {"locations": 330, "pct": 1, "amount": 1793470, "meters": 2, "meters_rdof": 2, "geoid": "280779603003"}, {"locations": 559, "pct": 0, "amount": 1783770, "meters": 1, "meters_rdof": 1, "geoid": "280790405002"}, {"locations": 317, "pct": 0, "amount": 1393110, "meters": 1, "meters_rdof": 1, "geoid": "280790405003"}, {"locations": 600, "pct": 0, "amount": 2969650, "meters": 2, "meters_rdof": 2, "geoid": "280859501001"}, {"locations": 254, "pct": 1, "amount": 660420, "meters": 2, "meters_rdof": 2, "geoid": "280859501002"}, {"locations": 238, "pct": 0, "amount": 449140, "meters": 1, "meters_rdof": 1, "geoid": "280859503001"}, {"locations": 373, "pct": 1, "amount": 859570, "meters": 2, "meters_rdof": 2, "geoid": "280859503002"}, {"locations": 452, "pct": 0, "amount": 1576170, "meters": 1, "meters_rdof": 1, "geoid": "280859503003"}, {"locations": 681, "pct": 0, "amount": 2435260, "meters": 1, "meters_rdof": 1, "geoid": "280859503004"}, {"locations": 407, "pct": 0, "amount": 706930, "meters": 1, "meters_rdof": 1, "geoid": "280859504001"}, {"locations": 608, "pct": 0, "amount": 1888070, "meters": 1, "meters_rdof": 1, "geoid": "280859504002"}, {"locations": 299, "pct": 0, "amount": 777360, "meters": 1, "meters_rdof": 1, "geoid": "280859504003"}, {"locations": 311, "pct": 0, "amount": 280210, "meters": 1, "meters_rdof": 1, "geoid": "280859504004"}, {"locations": 30, "pct": 3, "amount": 40620, "meters": 1, "meters_rdof": 1, "geoid": "280859505003"}, {"locations": 646, "pct": 0, "amount": 2225720, "meters": 1, "meters_rdof": 1, "geoid": "280919502002"}, {"locations": 450, "pct": 0, "amount": 623180, "meters": 1, "meters_rdof": 1, "geoid": "280919506002"}, {"locations": 445, "pct": 0, "amount": 860740, "meters": 1, "meters_rdof": 1, "geoid": "280919506003"}, {"locations": 347, "pct": 0, "amount": 1085470, "meters": 1, "meters_rdof": 1, "geoid": "280919506004"}, {"locations": 358, "pct": 0, "amount": 1435570, "meters": 1, "meters_rdof": 1, "geoid": "281010501001"}, {"locations": 333, "pct": 0, "amount": 1440840, "meters": 1, "meters_rdof": 1, "geoid": "281010501002"}, {"locations": 271, "pct": 0, "amount": 1225330, "meters": 1, "meters_rdof": 1, "geoid": "281010501003"}, {"locations": 200, "pct": 0, "amount": 1041230, "meters": 1, "meters_rdof": 1, "geoid": "281010502002"}, {"locations": 358, "pct": 0, "amount": 1444730, "meters": 1, "meters_rdof": 1, "geoid": "281010503002"}, {"locations": 301, "pct": 0, "amount": 1442930, "meters": 1, "meters_rdof": 1, "geoid": "281010503003"}, {"locations": 477, "pct": 0, "amount": 1389300, "meters": 1, "meters_rdof": 1, "geoid": "281010503004"}, {"locations": 26, "pct": 4, "amount": 126520, "meters": 1, "meters_rdof": 1, "geoid": "281010503005"}, {"locations": 374, "pct": 0, "amount": 1282740, "meters": 1, "meters_rdof": 1, "geoid": "281010504001"}, {"locations": 63, "pct": 2, "amount": 76060, "meters": 1, "meters_rdof": 1, "geoid": "281010504002"}, {"locations": 214, "pct": 0, "amount": 889510, "meters": 1, "meters_rdof": 1, "geoid": "281010504004"}, {"locations": 320, "pct": 0, "amount": 1636210, "meters": 1, "meters_rdof": 1, "geoid": "281010504005"}, {"locations": 7, "pct": 14, "amount": 12510, "meters": 1, "meters_rdof": 1, "geoid": "281010505001"}, {"locations": 25, "pct": 4, "amount": 45800, "meters": 1, "meters_rdof": 1, "geoid": "281010505002"}, {"locations": 8, "pct": 12, "amount": 15310, "meters": 1, "meters_rdof": 1, "geoid": "281010505003"}, {"locations": 2, "pct": 50, "amount": 2480, "meters": 1, "meters_rdof": 1, "geoid": "281010505004"}, {"locations": 27, "pct": 4, "amount": 30920, "meters": 1, "meters_rdof": 1, "geoid": "281139501011"}, {"locations": 441, "pct": 0, "amount": 994400, "meters": 1, "meters_rdof": 1, "geoid": "281139501012"}, {"locations": 638, "pct": 0, "amount": 1429580, "meters": 1, "meters_rdof": 1, "geoid": "281139501013"}, {"locations": 308, "pct": 0, "amount": 769840, "meters": 1, "meters_rdof": 1, "geoid": "281139501021"}, {"locations": 12, "pct": 8, "amount": 7760, "meters": 1, "meters_rdof": 1, "geoid": "281139501022"}, {"locations": 3, "pct": 33, "amount": 4060, "meters": 1, "meters_rdof": 1, "geoid": "281139502001"}, {"locations": 27, "pct": 4, "amount": 41780, "meters": 1, "meters_rdof": 1, "geoid": "281139502002"}, {"locations": 57, "pct": 2, "amount": 102510, "meters": 1, "meters_rdof": 1, "geoid": "281139502003"}, {"locations": 1, "pct": 100, "amount": 180, "meters": 1, "meters_rdof": 1, "geoid": "281139503002"}, {"locations": 17, "pct": 6, "amount": 2050, "meters": 1, "meters_rdof": 1, "geoid": "281139504002"}, {"locations": 11, "pct": 9, "amount": 15850, "meters": 1, "meters_rdof": 1, "geoid": "281139505001"}, {"locations": 191, "pct": 1, "amount": 232090, "meters": 1, "meters_rdof": 1, "geoid": "281139505002"}, {"locations": 84, "pct": 1, "amount": 168960, "meters": 1, "meters_rdof": 1, "geoid": "281139506001"}, {"locations": 2, "pct": 50, "amount": 6390, "meters": 1, "meters_rdof": 1, "geoid": "281139506002"}, {"locations": 376, "pct": 0, "amount": 479730, "meters": 1, "meters_rdof": 1, "geoid": "281139506003"}, {"locations": 545, "pct": 0, "amount": 1037040, "meters": 1, "meters_rdof": 1, "geoid": "281139506004"}, {"locations": 672, "pct": 0, "amount": 2174700, "meters": 1, "meters_rdof": 1, "geoid": "281139507001"}, {"locations": 534, "pct": 0, "amount": 1428170, "meters": 1, "meters_rdof": 1, "geoid": "281139507002"}, {"locations": 331, "pct": 0, "amount": 698440, "meters": 1, "meters_rdof": 1, "geoid": "281139507003"}, {"locations": 319, "pct": 0, "amount": 1018230, "meters": 1, "meters_rdof": 1, "geoid": "281139507004"}, {"locations": 385, "pct": 0, "amount": 863890, "meters": 1, "meters_rdof": 1, "geoid": "281210201013"}, {"locations": 268, "pct": 0, "amount": 671720, "meters": 1, "meters_rdof": 1, "geoid": "281210201021"}, {"locations": 44, "pct": 2, "amount": 10820, "meters": 1, "meters_rdof": 1, "geoid": "281210202071"}, {"locations": 5, "pct": 20, "amount": 26330, "meters": 1, "meters_rdof": 1, "geoid": "281210202074"}, {"locations": 4, "pct": 25, "amount": 640, "meters": 1, "meters_rdof": 1, "geoid": "281210202082"}, {"locations": 12, "pct": 8, "amount": 16760, "meters": 1, "meters_rdof": 1, "geoid": "281210204021"}, {"locations": 1, "pct": 100, "amount": 1690, "meters": 1, "meters_rdof": 1, "geoid": "281210204023"}, {"locations": 4, "pct": 25, "amount": 11070, "meters": 1, "meters_rdof": 1, "geoid": "281210205002"}, {"locations": 2, "pct": 50, "amount": 300, "meters": 1, "meters_rdof": 1, "geoid": "281210207031"}, {"locations": 2, "pct": 50, "amount": 3020, "meters": 1, "meters_rdof": 1, "geoid": "281210208021"}, {"locations": 1, "pct": 100, "amount": 720, "meters": 1, "meters_rdof": 1, "geoid": "281210208023"}, {"locations": 3, "pct": 33, "amount": 20750, "meters": 1, "meters_rdof": 1, "geoid": "281210208024"}, {"locations": 10, "pct": 10, "amount": 25040, "meters": 1, "meters_rdof": 1, "geoid": "281210208025"}, {"locations": 3, "pct": 33, "amount": 10280, "meters": 1, "meters_rdof": 1, "geoid": "281210208031"}, {"locations": 214, "pct": 0, "amount": 555040, "meters": 1, "meters_rdof": 1, "geoid": "281210209001"}, {"locations": 55, "pct": 2, "amount": 428210, "meters": 1, "meters_rdof": 1, "geoid": "281210209002"}, {"locations": 176, "pct": 1, "amount": 724180, "meters": 1, "meters_rdof": 1, "geoid": "281210209003"}, {"locations": 161, "pct": 1, "amount": 502000, "meters": 1, "meters_rdof": 1, "geoid": "281210209004"}, {"locations": 1, "pct": 100, "amount": 180, "meters": 1, "meters_rdof": 1, "geoid": "281210210012"}, {"locations": 39, "pct": 3, "amount": 397240, "meters": 1, "meters_rdof": 1, "geoid": "281210210021"}, {"locations": 2, "pct": 50, "amount": 2910, "meters": 1, "meters_rdof": 1, "geoid": "281210210022"}, {"locations": 6, "pct": 17, "amount": 84230, "meters": 1, "meters_rdof": 1, "geoid": "281210210023"}, {"locations": 19, "pct": 5, "amount": 6220, "meters": 1, "meters_rdof": 1, "geoid": "281210210024"}, {"locations": 68, "pct": 1, "amount": 136960, "meters": 1, "meters_rdof": 1, "geoid": "281210210032"}, {"locations": 286, "pct": 0, "amount": 300310, "meters": 1, "meters_rdof": 1, "geoid": "281230202001"}, {"locations": 375, "pct": 0, "amount": 1301610, "meters": 1, "meters_rdof": 1, "geoid": "281230202002"}, {"locations": 484, "pct": 0, "amount": 2453320, "meters": 1, "meters_rdof": 1, "geoid": "281230202003"}, {"locations": 631, "pct": 0, "amount": 2506700, "meters": 1, "meters_rdof": 1, "geoid": "281230202004"}, {"locations": 638, "pct": 0, "amount": 1893200, "meters": 1, "meters_rdof": 1, "geoid": "281230203001"}, {"locations": 265, "pct": 0, "amount": 458580, "meters": 1, "meters_rdof": 1, "geoid": "281230203002"}, {"locations": 375, "pct": 0, "amount": 1097020, "meters": 1, "meters_rdof": 1, "geoid": "281230203003"}, {"locations": 2, "pct": 50, "amount": 2250, "meters": 1, "meters_rdof": 1, "geoid": "281230204001"}, {"locations": 17, "pct": 6, "amount": 14230, "meters": 1, "meters_rdof": 1, "geoid": "281230204002"}, {"locations": 1, "pct": 100, "amount": 490, "meters": 1, "meters_rdof": 1, "geoid": "281230204003"}, {"locations": 20, "pct": 5, "amount": 28980, "meters": 1, "meters_rdof": 1, "geoid": "281230205003"}, {"locations": 17, "pct": 6, "amount": 36630, "meters": 1, "meters_rdof": 1, "geoid": "281230205004"}, {"locations": 115, "pct": 1, "amount": 446510, "meters": 1, "meters_rdof": 1, "geoid": "281230206001"}, {"locations": 280, "pct": 0, "amount": 797320, "meters": 1, "meters_rdof": 1, "geoid": "281230206002"}, {"locations": 141, "pct": 1, "amount": 339400, "meters": 1, "meters_rdof": 1, "geoid": "281230206003"}, {"locations": 335, "pct": 0, "amount": 1675740, "meters": 1, "meters_rdof": 1, "geoid": "281279501001"}, {"locations": 298, "pct": 0, "amount": 893810, "meters": 1, "meters_rdof": 1, "geoid": "281279501002"}, {"locations": 94, "pct": 1, "amount": 121200, "meters": 1, "meters_rdof": 1, "geoid": "281279501003"}, {"locations": 420, "pct": 0, "amount": 1340410, "meters": 1, "meters_rdof": 1, "geoid": "281279501004"}, {"locations": 524, "pct": 0, "amount": 1167040, "meters": 1, "meters_rdof": 1, "geoid": "281279501005"}, {"locations": 24, "pct": 4, "amount": 26140, "meters": 1, "meters_rdof": 1, "geoid": "281279502001"}, {"locations": 80, "pct": 1, "amount": 236220, "meters": 1, "meters_rdof": 1, "geoid": "281279502004"}, {"locations": 244, "pct": 0, "amount": 560970, "meters": 1, "meters_rdof": 1, "geoid": "281279503001"}, {"locations": 187, "pct": 1, "amount": 617040, "meters": 1, "meters_rdof": 1, "geoid": "281279503002"}, {"locations": 155, "pct": 1, "amount": 1025220, "meters": 1, "meters_rdof": 1, "geoid": "281279503003"}, {"locations": 530, "pct": 0, "amount": 2082360, "meters": 1, "meters_rdof": 1, "geoid": "281279503004"}, {"locations": 212, "pct": 0, "amount": 508320, "meters": 1, "meters_rdof": 1, "geoid": "281279504001"}, {"locations": 277, "pct": 0, "amount": 579090, "meters": 1, "meters_rdof": 1, "geoid": "281279504002"}, {"locations": 195, "pct": 1, "amount": 262940, "meters": 1, "meters_rdof": 1, "geoid": "281279504003"}, {"locations": 262, "pct": 0, "amount": 759680, "meters": 1, "meters_rdof": 1, "geoid": "281279504004"}, {"locations": 360, "pct": 0, "amount": 1561150, "meters": 1, "meters_rdof": 1, "geoid": "281279504005"}, {"locations": 358, "pct": 0, "amount": 1389030, "meters": 1, "meters_rdof": 1, "geoid": "281279504006"}, {"locations": 308, "pct": 0, "amount": 2045150, "meters": 1, "meters_rdof": 1, "geoid": "281279504007"}, {"locations": 263, "pct": 0, "amount": 1268150, "meters": 1, "meters_rdof": 1, "geoid": "281279504008"}, {"locations": 42, "pct": 2, "amount": 91380, "meters": 1, "meters_rdof": 1, "geoid": "281279505001"}, {"locations": 1, "pct": 100, "amount": 260, "meters": 1, "meters_rdof": 1, "geoid": "281279505002"}, {"locations": 58, "pct": 2, "amount": 147430, "meters": 1, "meters_rdof": 1, "geoid": "281279505003"}, {"locations": 11, "pct": 9, "amount": 19690, "meters": 1, "meters_rdof": 1, "geoid": "281279505004"}, {"locations": 13, "pct": 8, "amount": 90760, "meters": 1, "meters_rdof": 1, "geoid": "281299501002"}, {"locations": 79, "pct": 1, "amount": 756750, "meters": 1, "meters_rdof": 1, "geoid": "281299501004"}, {"locations": 91, "pct": 1, "amount": 326400, "meters": 1, "meters_rdof": 1, "geoid": "281299502001"}, {"locations": 140, "pct": 1, "amount": 1065790, "meters": 1, "meters_rdof": 1, "geoid": "281299502002"}, {"locations": 409, "pct": 0, "amount": 1930740, "meters": 1, "meters_rdof": 1, "geoid": "281299502003"}, {"locations": 274, "pct": 0, "amount": 1446800, "meters": 1, "meters_rdof": 1, "geoid": "281299502004"}, {"locations": 542, "pct": 0, "amount": 2202490, "meters": 1, "meters_rdof": 1, "geoid": "281299502005"}, {"locations": 333, "pct": 0, "amount": 1379520, "meters": 1, "meters_rdof": 1, "geoid": "281299502006"}, {"locations": 121, "pct": 1, "amount": 748770, "meters": 1, "meters_rdof": 1, "geoid": "281299503001"}, {"locations": 216, "pct": 0, "amount": 994210, "meters": 1, "meters_rdof": 1, "geoid": "281299503002"}, {"locations": 6, "pct": 17, "amount": 3800, "meters": 1, "meters_rdof": 1, "geoid": "281299503003"}, {"locations": 85, "pct": 1, "amount": 204670, "meters": 1, "meters_rdof": 1, "geoid": "281299503004"}, {"locations": 291, "pct": 0, "amount": 588280, "meters": 1, "meters_rdof": 1, "geoid": "281299503005"}, {"locations": 361, "pct": 0, "amount": 1687220, "meters": 1, "meters_rdof": 1, "geoid": "281479501001"}, {"locations": 769, "pct": 0, "amount": 1483260, "meters": 1, "meters_rdof": 1, "geoid": "281479501002"}, {"locations": 456, "pct": 0, "amount": 838640, "meters": 1, "meters_rdof": 1, "geoid": "281479501003"}, {"locations": 250, "pct": 0, "amount": 627670, "meters": 1, "meters_rdof": 1, "geoid": "281479501004"}, {"locations": 254, "pct": 0, "amount": 583270, "meters": 1, "meters_rdof": 1, "geoid": "281479501005"}, {"locations": 228, "pct": 0, "amount": 885370, "meters": 1, "meters_rdof": 1, "geoid": "281479501006"}, {"locations": 60, "pct": 2, "amount": 67930, "meters": 1, "meters_rdof": 1, "geoid": "281479502001"}, {"locations": 38, "pct": 3, "amount": 15570, "meters": 1, "meters_rdof": 1, "geoid": "281479502002"}, {"locations": 566, "pct": 0, "amount": 1350720, "meters": 1, "meters_rdof": 1, "geoid": "281479503001"}, {"locations": 840, "pct": 0, "amount": 1515480, "meters": 1, "meters_rdof": 1, "geoid": "281479503002"}, {"locations": 301, "pct": 0, "amount": 663400, "meters": 1, "meters_rdof": 1, "geoid": "281479503003"}, {"locations": 680, "pct": 0, "amount": 2194880, "meters": 1, "meters_rdof": 1, "geoid": "281479503004"}, {"locations": 682, "pct": 0, "amount": 3018340, "meters": 1, "meters_rdof": 1, "geoid": "281479503005"}, {"locations": 418, "pct": 0, "amount": 2274500, "meters": 1, "meters_rdof": 1, "geoid": "281539503001"}]