[{"locations": 511, "pct": 59, "amount": 4938600, "meters": 316, "meters_no_service": 316, "meters_underserved": 0, "meters_fiber": 0, "meters_rdof": 300, "meters_cable": 0, "geoid": "410110002002", "meters_telco": 0}, {"locations": 175, "pct": 65, "amount": 793960, "meters": 117, "meters_no_service": 117, "meters_underserved": 0, "meters_fiber": 0, "meters_rdof": 113, "meters_cable": 0, "geoid": "410110002003", "meters_telco": 0}, {"locations": 30, "pct": 147, "amount": 326630, "meters": 175, "meters_no_service": 52, "meters_underserved": 25, "meters_fiber": 0, "meters_rdof": 44, "meters_cable": 98, "geoid": "410110005022", "meters_telco": 69}, {"locations": 17, "pct": 82, "amount": 54840, "meters": 69, "meters_no_service": 14, "meters_underserved": 0, "meters_fiber": 0, "meters_rdof": 14, "meters_cable": 55, "geoid": "410110008001", "meters_telco": 69}, {"locations": 179, "pct": 53, "amount": 628850, "meters": 118, "meters_no_service": 98, "meters_underserved": 0, "meters_fiber": 20, "meters_rdof": 95, "meters_cable": 20, "geoid": "410110009001", "meters_telco": 20}, {"locations": 83, "pct": 1, "amount": 120250, "meters": 1, "meters_no_service": 0, "meters_underserved": 1, "meters_fiber": 0, "meters_rdof": 1, "meters_cable": 0, "geoid": "410110009002", "meters_telco": 1}, {"locations": 122, "pct": 94, "amount": 951940, "meters": 148, "meters_no_service": 72, "meters_underserved": 46, "meters_fiber": 0, "meters_rdof": 115, "meters_cable": 30, "geoid": "410110009007", "meters_telco": 76}, {"locations": 317, "pct": 56, "amount": 1173360, "meters": 184, "meters_no_service": 179, "meters_underserved": 5, "meters_fiber": 0, "meters_rdof": 176, "meters_cable": 0, "geoid": "410110009008", "meters_telco": 154}, {"locations": 128, "pct": 42, "amount": 1506460, "meters": 329, "meters_no_service": 6, "meters_underserved": 55, "meters_fiber": 0, "meters_rdof": 54, "meters_cable": 268, "geoid": "410110010001", "meters_telco": 322}, {"locations": 5, "pct": 80, "amount": 4310, "meters": 32, "meters_no_service": 0, "meters_underserved": 4, "meters_fiber": 27, "meters_rdof": 4, "meters_cable": 28, "geoid": "410110010004", "meters_telco": 32}, {"locations": 11, "pct": 9, "amount": 54100, "meters": 44, "meters_no_service": 1, "meters_underserved": 0, "meters_fiber": 0, "meters_rdof": 1, "meters_cable": 43, "geoid": "410110010005", "meters_telco": 43}, {"locations": 130, "pct": 81, "amount": 715200, "meters": 190, "meters_no_service": 40, "meters_underserved": 71, "meters_fiber": 0, "meters_rdof": 105, "meters_cable": 79, "geoid": "410110010006", "meters_telco": 187}, {"locations": 102, "pct": 95, "amount": 782370, "meters": 397, "meters_no_service": 128, "meters_underserved": 58, "meters_fiber": 35, "meters_rdof": 97, "meters_cable": 210, "geoid": "410110010007", "meters_telco": 337}, {"locations": 280, "pct": 71, "amount": 2682670, "meters": 305, "meters_no_service": 257, "meters_underserved": 34, "meters_fiber": 0, "meters_rdof": 199, "meters_cable": 14, "geoid": "410110011001", "meters_telco": 34}, {"locations": 363, "pct": 90, "amount": 3237440, "meters": 352, "meters_no_service": 191, "meters_underserved": 161, "meters_fiber": 0, "meters_rdof": 326, "meters_cable": 0, "geoid": "410110011002", "meters_telco": 304}, {"locations": 1, "pct": 300, "amount": 3600, "meters": 12, "meters_no_service": 3, "meters_underserved": 0, "meters_fiber": 0, "meters_rdof": 3, "meters_cable": 9, "geoid": "410110011004", "meters_telco": 12}, {"locations": 216, "pct": 30, "amount": 1620200, "meters": 136, "meters_no_service": 67, "meters_underserved": 0, "meters_fiber": 0, "meters_rdof": 64, "meters_cable": 69, "geoid": "410110011005", "meters_telco": 70}, {"locations": 135, "pct": 94, "amount": 1320900, "meters": 136, "meters_no_service": 63, "meters_underserved": 69, "meters_fiber": 2, "meters_rdof": 127, "meters_cable": 4, "geoid": "410110011006", "meters_telco": 110}, {"locations": 137, "pct": 23, "amount": 1882840, "meters": 101, "meters_no_service": 98, "meters_underserved": 3, "meters_fiber": 0, "meters_rdof": 31, "meters_cable": 0, "geoid": "410110011007", "meters_telco": 43}, {"locations": 205, "pct": 92, "amount": 3616430, "meters": 814, "meters_no_service": 280, "meters_underserved": 35, "meters_fiber": 0, "meters_rdof": 188, "meters_cable": 500, "geoid": "410159501001", "meters_telco": 307}, {"locations": 23, "pct": 91, "amount": 239760, "meters": 826, "meters_no_service": 12, "meters_underserved": 21, "meters_fiber": 0, "meters_rdof": 21, "meters_cable": 793, "geoid": "410159501002", "meters_telco": 723}, {"locations": 14, "pct": 79, "amount": 178890, "meters": 1269, "meters_no_service": 15, "meters_underserved": 10, "meters_fiber": 0, "meters_rdof": 11, "meters_cable": 1244, "geoid": "410159502001", "meters_telco": 949}, {"locations": 55, "pct": 105, "amount": 263780, "meters": 1114, "meters_no_service": 21, "meters_underserved": 73, "meters_fiber": 41, "meters_rdof": 58, "meters_cable": 1020, "geoid": "410159502002", "meters_telco": 936}, {"locations": 138, "pct": 122, "amount": 1501650, "meters": 1391, "meters_no_service": 68, "meters_underserved": 121, "meters_fiber": 0, "meters_rdof": 168, "meters_cable": 1202, "geoid": "410159502003", "meters_telco": 1150}, {"locations": 122, "pct": 126, "amount": 1905030, "meters": 1409, "meters_no_service": 136, "meters_underserved": 74, "meters_fiber": 0, "meters_rdof": 154, "meters_cable": 1199, "geoid": "410159503011", "meters_telco": 1295}, {"locations": 6, "pct": 33, "amount": 136770, "meters": 461, "meters_no_service": 2, "meters_underserved": 1, "meters_fiber": 0, "meters_rdof": 2, "meters_cable": 458, "geoid": "410159503012", "meters_telco": 441}, {"locations": 147, "pct": 81, "amount": 1677970, "meters": 907, "meters_no_service": 129, "meters_underserved": 0, "meters_fiber": 0, "meters_rdof": 119, "meters_cable": 779, "geoid": "410159504003", "meters_telco": 777}, {"locations": 8, "pct": 38, "amount": 115800, "meters": 5, "meters_no_service": 2, "meters_underserved": 3, "meters_fiber": 0, "meters_rdof": 3, "meters_cable": 0, "geoid": "410191700002", "meters_telco": 3}]